k8/__init__.py
k8/admissionregistration_v1_service_reference.py
k8/admissionregistration_v1_webhook_client_config.py
k8/apiextensions_v1_service_reference.py
k8/apiextensions_v1_webhook_client_config.py
k8/apiregistration_v1_service_reference.py
k8/authentication_v1_token_request.py
k8/core_v1_endpoint_port.py
k8/core_v1_event.py
k8/core_v1_event_list.py
k8/core_v1_event_series.py
k8/discovery_v1_endpoint_port.py
k8/events_v1_event.py
k8/events_v1_event_list.py
k8/events_v1_event_series.py
k8/flowcontrol_v1_subject.py
k8/py.typed
k8/rbac_v1_subject.py
k8/storage_v1_token_request.py
k8/v1_affinity.py
k8/v1_aggregation_rule.py
k8/v1_api_group.py
k8/v1_api_group_list.py
k8/v1_api_resource.py
k8/v1_api_resource_list.py
k8/v1_api_service.py
k8/v1_api_service_condition.py
k8/v1_api_service_list.py
k8/v1_api_service_spec.py
k8/v1_api_service_status.py
k8/v1_api_versions.py
k8/v1_attached_volume.py
k8/v1_aws_elastic_block_store_volume_source.py
k8/v1_azure_disk_volume_source.py
k8/v1_azure_file_persistent_volume_source.py
k8/v1_azure_file_volume_source.py
k8/v1_binding.py
k8/v1_bound_object_reference.py
k8/v1_capabilities.py
k8/v1_ceph_fs_persistent_volume_source.py
k8/v1_ceph_fs_volume_source.py
k8/v1_certificate_signing_request.py
k8/v1_certificate_signing_request_condition.py
k8/v1_certificate_signing_request_list.py
k8/v1_certificate_signing_request_spec.py
k8/v1_certificate_signing_request_status.py
k8/v1_cinder_persistent_volume_source.py
k8/v1_cinder_volume_source.py
k8/v1_claim_source.py
k8/v1_client_ip_config.py
k8/v1_cluster_role.py
k8/v1_cluster_role_binding.py
k8/v1_cluster_role_binding_list.py
k8/v1_cluster_role_list.py
k8/v1_cluster_trust_bundle_projection.py
k8/v1_component_condition.py
k8/v1_component_status.py
k8/v1_component_status_list.py
k8/v1_condition.py
k8/v1_config_map.py
k8/v1_config_map_env_source.py
k8/v1_config_map_key_selector.py
k8/v1_config_map_list.py
k8/v1_config_map_node_config_source.py
k8/v1_config_map_projection.py
k8-29.0.9.dist-info/LICENSE
k8-29.0.9.dist-info/METADATA
k8-29.0.9.dist-info/WHEEL
k8-29.0.9.dist-info/top_level.txt
k8-29.0.9.dist-info/RECORD
