Metadata-Version: 2.1
Name: k8
Version: 29.0.9
Summary: Kubernetes Python Models
Author-email: Nick Cooper <nick@not.fun>
Project-URL: Homepage, https://github.com/nicknotfun/k8
Project-URL: Issues, https://github.com/nicknotfun/k8/issues
Keywords: OpenAPI,OpenAPI-Generator,Kubernetes
Classifier: Programming Language :: Python :: 3
Classifier: License :: OSI Approved :: MIT License
Classifier: Operating System :: OS Independent
Requires-Python: >=3.11
License-File: LICENSE
Requires-Dist: pydantic >=2
Requires-Dist: aenum >=3.1.11
